README.md
setup.cfg
setup.py
examples/__init__.py
polytropos/__init__.py
polytropos/cli.py
polytropos.egg-info/PKG-INFO
polytropos.egg-info/SOURCES.txt
polytropos.egg-info/dependency_links.txt
polytropos.egg-info/entry_points.txt
polytropos.egg-info/requires.txt
polytropos.egg-info/top_level.txt
polytropos/actions/__init__.py
polytropos/actions/step.py
polytropos/actions/aggregate/__init__.py
polytropos/actions/aggregate/_aggregate.py
polytropos/actions/changes/__init__.py
polytropos/actions/changes/available.py
polytropos/actions/changes/available_v2.py
polytropos/actions/changes/cast.py
polytropos/actions/changes/delete.py
polytropos/actions/changes/display.py
polytropos/actions/changes/prune.py
polytropos/actions/changes/sort.py
polytropos/actions/changes/universal.py
polytropos/actions/changes/stat/__init__.py
polytropos/actions/changes/stat/cross_sectional/__init__.py
polytropos/actions/changes/stat/cross_sectional/iterators.py
polytropos/actions/changes/stat/cross_sectional/minmax.py
polytropos/actions/changes/stat/cross_sectional/reduce.py
polytropos/actions/changes/stat/cross_sectional/univariate.py
polytropos/actions/changes/stat/longitudinal/__init__.py
polytropos/actions/changes/stat/longitudinal/minmax.py
polytropos/actions/changes/stat/longitudinal/reduce.py
polytropos/actions/changes/stat/longitudinal/univariate.py
polytropos/actions/consume/__init__.py
polytropos/actions/consume/_consume.py
polytropos/actions/consume/coverage.py
polytropos/actions/consume/tojson.py
polytropos/actions/consume/sourcecoverage/__init__.py
polytropos/actions/consume/sourcecoverage/crawl.py
polytropos/actions/consume/sourcecoverage/extract.py
polytropos/actions/consume/sourcecoverage/pair.py
polytropos/actions/consume/sourcecoverage/result.py
polytropos/actions/consume/sourcecoverage/sourcecoverage.py
polytropos/actions/consume/tocsv/__init__.py
polytropos/actions/consume/tocsv/tocsv.py
polytropos/actions/consume/tocsv/topo.py
polytropos/actions/consume/tocsv/blocks/__init__.py
polytropos/actions/consume/tocsv/blocks/_blocks.py
polytropos/actions/consume/tocsv/blocks/blockvalue.py
polytropos/actions/consume/tocsv/blocks/product.py
