Metadata-Version: 2.1
Name: polytropos
Version: 1.6.16
Summary: UNKNOWN
Home-page: https://github.com/borenstein/polytropos
License: agpl-3.0
Platform: UNKNOWN
Classifier: Development Status :: 3 - Alpha
Classifier: Intended Audience :: Developers
Classifier: Topic :: Software Development :: Build Tools
Classifier: Programming Language :: Python :: 3.7
